NowTCP/NowTCP.py
NowTCP/__init__.py
NowTCP-0.0.4.dist-info/METADATA
NowTCP-0.0.4.dist-info/RECORD
NowTCP-0.0.4.dist-info/WHEEL
NowTCP-0.0.4.dist-info/top_level.txt
