Metadata-Version: 2.1
Name: NowTCP
Version: 0.0.4
Summary: 🌀 NowTCP - Fast create your TCP Server/Client 🌀
Home-page: https://github.com/truedl/NowTCP
Author: truedl
Author-email: dauzduz1@gmail.com
License: MIT
Platform: UNKNOWN
